Bubbles1/Demo_video.py
Bubbles1/NNDemo.py
Bubbles1/__init__.py
Bubbles1/nnAPI.py
Bubbles1-1.0.4.dist-info/LICENCE.txt
Bubbles1-1.0.4.dist-info/METADATA
Bubbles1-1.0.4.dist-info/WHEEL
Bubbles1-1.0.4.dist-info/entry_points.txt
Bubbles1-1.0.4.dist-info/top_level.txt
Bubbles1-1.0.4.dist-info/RECORD
