Metadata-Version: 2.1
Name: Bubbles1
Version: 1.0.4
Summary: Kinetiq_Library
Home-page: UNKNOWN
Author: Sujata
Author-email: UNKNOWN
License: MIT
Platform: UNKNOWN
Classifier: License :: OSI Approved :: MIT License
Classifier: Programming Language :: Python :: 3
Classifier: Programming Language :: Python :: 3.8
